hearken/__init__.py
hearken/detector.py
hearken/interfaces.py
hearken/listener.py
hearken/types.py
hearken/adapters/__init__.py
hearken/adapters/sr.py
hearken/vad/__init__.py
hearken/vad/energy.py
hearken/vad/silero.py
hearken/vad/webrtc.py
hearken-0.4.0.dist-info/METADATA
hearken-0.4.0.dist-info/WHEEL
hearken-0.4.0.dist-info/licenses/LICENSE
hearken-0.4.0.dist-info/RECORD
