Metadata-Version: 2.4
Name: hearken
Version: 0.4.0
Summary: Robust speech recognition pipeline that prevents audio drops
Project-URL: Homepage, https://github.com/hipsterbrown/hearken
Project-URL: Documentation, https://github.com/hipsterbrown/hearken#readme
Project-URL: Repository, https://github.com/hipsterbrown/hearken
Project-URL: Issues, https://github.com/hipsterbrown/hearken/issues
Author-email: Nick Hehr <headhipster@hipsterbrown.com>
License: Apache 2.0
License-File: LICENSE
Keywords: audio,speech-recognition,transcription,vad,voice
Classifier: Development Status :: 3 - Alpha
Classifier: Intended Audience :: Developers
Classifier: License :: OSI Approved :: Apache Software License
Classifier: Programming Language :: Python :: 3
Classifier: Programming Language :: Python :: 3.11
Classifier: Programming Language :: Python :: 3.12
Classifier: Programming Language :: Python :: 3.13
Classifier: Topic :: Multimedia :: Sound/Audio :: Speech
Requires-Python: >=3.11
Requires-Dist: numpy>=1.20
Provides-Extra: all
Requires-Dist: onnxruntime>=1.16.0; extra == 'all'
Requires-Dist: pyaudio>=0.2.11; extra == 'all'
Requires-Dist: speechrecognition>=3.8; extra == 'all'
Requires-Dist: webrtcvad-wheels>=2.0.10; extra == 'all'
Provides-Extra: dev
Requires-Dist: black>=23.0; extra == 'dev'
Requires-Dist: mypy>=1.0; extra == 'dev'
Requires-Dist: pytest-cov>=4.0; extra == 'dev'
Requires-Dist: pytest>=7.0; extra == 'dev'
Requires-Dist: ruff>=0.1.0; extra == 'dev'
Provides-Extra: silero
Requires-Dist: onnxruntime>=1.16.0; extra == 'silero'
Provides-Extra: sr
Requires-Dist: pyaudio>=0.2.11; extra == 'sr'
Requires-Dist: speechrecognition>=3.8; extra == 'sr'
Provides-Extra: webrtc
Requires-Dist: webrtcvad-wheels>=2.0.10; extra == 'webrtc'
